lib/distclean.sh
lib/install.sh
lib/uninstall.sh
lib/etc/udev/rules.d/85-qhyccd.rules
lib/lib/firmware/qhy/IC16200A.HEX
lib/lib/firmware/qhy/IC16803.HEX
lib/lib/firmware/qhy/IC8300.HEX
lib/lib/firmware/qhy/IC90A.HEX
lib/lib/firmware/qhy/IMG0H.HEX
lib/lib/firmware/qhy/IMG2P.HEX
lib/lib/firmware/qhy/IMG2S.HEX
lib/lib/firmware/qhy/IMG50.HEX
lib/lib/firmware/qhy/POLEMASTER.HEX
lib/lib/firmware/qhy/QHY0204.img
lib/lib/firmware/qhy/QHY09000A.HEX
lib/lib/firmware/qhy/QHY10.HEX
lib/lib/firmware/qhy/QHY11.HEX
lib/lib/firmware/qhy/QHY12.HEX
lib/lib/firmware/qhy/QHY128.img
lib/lib/firmware/qhy/QHY15.HEX
lib/lib/firmware/qhy/QHY16.HEX
lib/lib/firmware/qhy/QHY16000.HEX
lib/lib/firmware/qhy/QHY160002AD.HEX
lib/lib/firmware/qhy/QHY16200A.HEX
lib/lib/firmware/qhy/QHY163.img
lib/lib/firmware/qhy/QHY165.img
lib/lib/firmware/qhy/QHY168.img
lib/lib/firmware/qhy/QHY16803A.HEX
lib/lib/firmware/qhy/QHY174.img
lib/lib/firmware/qhy/QHY178.img
lib/lib/firmware/qhy/QHY183.img
lib/lib/firmware/qhy/QHY2.HEX
lib/lib/firmware/qhy/QHY20.HEX
lib/lib/firmware/qhy/QHY2020.img
lib/lib/firmware/qhy/QHY21.HEX
lib/lib/firmware/qhy/QHY22.HEX
lib/lib/firmware/qhy/QHY224.img
lib/lib/firmware/qhy/QHY23.HEX
lib/lib/firmware/qhy/QHY247.img
lib/lib/firmware/qhy/QHY27.HEX
lib/lib/firmware/qhy/QHY28.HEX
lib/lib/firmware/qhy/QHY29.HEX
lib/lib/firmware/qhy/QHY290.img
lib/lib/firmware/qhy/QHY294.img
lib/lib/firmware/qhy/QHY2E.HEX
lib/lib/firmware/qhy/QHY2PRO.HEX
lib/lib/firmware/qhy/QHY367.img
lib/lib/firmware/qhy/QHY4040.img
lib/lib/firmware/qhy/QHY411.img
lib/lib/firmware/qhy/QHY411ERIS.img
lib/lib/firmware/qhy/QHY42.img
lib/lib/firmware/qhy/QHY42PRO.img
lib/lib/firmware/qhy/QHY5.HEX
lib/lib/firmware/qhy/QHY550.img
lib/lib/firmware/qhy/QHY5II.HEX
lib/lib/firmware/qhy/QHY5III174.img
lib/lib/firmware/qhy/QHY5III178.img
lib/lib/firmware/qhy/QHY5III185.img
lib/lib/firmware/qhy/QHY5III224.img
lib/lib/firmware/qhy/QHY5III290.img
lib/lib/firmware/qhy/QHY5LOADER.HEX
lib/lib/firmware/qhy/QHY6.HEX
pyobs_qhyccd-1.4.0.dist-info/METADATA
pyobs_qhyccd-1.4.0.dist-info/WHEEL
pyobs_qhyccd-1.4.0.dist-info/RECORD
