Metadata-Version: 2.4
Name: pyobs-qhyccd
Version: 1.4.0
Summary: pyobs module for QHYCCD cameras
Author-email: Tim-Oliver Husser <thusser@uni-goettingen.de>
License-Expression: MIT
Requires-Python: >=3.11
Requires-Dist: astropy<8,>=7.0.1
Requires-Dist: numpy<3,>=2.2.5
Requires-Dist: pyobs-core<2,>=1
